snars/__init__.py
snars/core.py
snars/utils.py
snras-1.0.0.dist-info/licenses/LICENSE
snras-1.0.0.dist-info/METADATA
snras-1.0.0.dist-info/WHEEL
snras-1.0.0.dist-info/top_level.txt
snras-1.0.0.dist-info/RECORD
